.gitignore
example.py
setup.py
ebs/__init__.py
ebs/linuxnode/__init__.py
ebs/linuxnode/sysinfo/__init__.py
ebs/linuxnode/sysinfo/app.py
ebs/linuxnode/sysinfo/base.py
ebs/linuxnode/sysinfo/config.py
ebs/linuxnode/sysinfo/cpu.py
ebs/linuxnode/sysinfo/disks.py
ebs/linuxnode/sysinfo/display.py
ebs/linuxnode/sysinfo/host.py
ebs/linuxnode/sysinfo/memory.py
ebs/linuxnode/sysinfo/mixin.py
ebs/linuxnode/sysinfo/network.py
ebs/linuxnode/sysinfo/status.py
ebs/linuxnode/sysinfo/temperature.py
ebs/linuxnode/sysinfo/versions.py
ebs_linuxnode_sysinfo.egg-info/PKG-INFO
ebs_linuxnode_sysinfo.egg-info/SOURCES.txt
ebs_linuxnode_sysinfo.egg-info/dependency_links.txt
ebs_linuxnode_sysinfo.egg-info/requires.txt
ebs_linuxnode_sysinfo.egg-info/top_level.txt